springust/__init__.py
springust/command/__init__.py
springust/command/generate.py
springust/springust.py
springust-0.1.0.dist-info/entry_points.txt
springust-0.1.0.dist-info/LICENSE
springust-0.1.0.dist-info/WHEEL
springust-0.1.0.dist-info/METADATA
springust-0.1.0.dist-info/RECORD
