Metadata-Version: 2.1
Name: springust
Version: 0.1.0
Summary: springust
Author: Boris Korogvich
Author-email: b.korogvich@gmail.com
Requires-Python: >=3.7,<4.0
Classifier: Programming Language :: Python :: 3
Classifier: Programming Language :: Python :: 3.7
